l3d/__init__.py
l3d/l3d.pyd
l3d_rs_python-0.2.3.dist-info/METADATA
l3d_rs_python-0.2.3.dist-info/WHEEL
l3d_rs_python-0.2.3.dist-info/RECORD
