Metadata-Version: 2.4
Name: l3d-rs-python
Version: 0.2.3
Classifier: Programming Language :: Rust
Classifier: Programming Language :: Python :: Implementation :: CPython
Classifier: Programming Language :: Python :: Implementation :: PyPy
Classifier: Development Status :: 4 - Beta
Classifier: Intended Audience :: Developers
Classifier: License :: OSI Approved :: MIT License
Classifier: License :: OSI Approved :: GNU General Public License v3 or later (GPLv3+)
Classifier: Topic :: Scientific/Engineering
Summary: Python bindings for l3d-rs - L3D luminaire file format parser
Keywords: l3d,luminaire,lighting,3d,gldf
License: MIT OR GPL-3.0-or-later
Requires-Python: >=3.9
Project-URL: Repository, https://github.com/holg/l3d-rs
